navalmartin_mir_db_utils/__init__.py
navalmartin_mir_db_utils/crud/__init__.py
navalmartin_mir_db_utils/crud/crud_utils.py
navalmartin_mir_db_utils/crud/index_utils.py
navalmartin_mir_db_utils/crud/mongodb_crud_ops.py
navalmartin_mir_db_utils/crud/mongodb_response_adaptors.py
navalmartin_mir_db_utils/crud/task_utils.py
navalmartin_mir_db_utils/dbs/__init__.py
navalmartin_mir_db_utils/dbs/dbs_utils.py
navalmartin_mir_db_utils/dbs/mongodb_session.py
navalmartin_mir_db_utils/examples/__init__.py
navalmartin_mir_db_utils/examples/monitoring_tasks.py
navalmartin_mir_db_utils/examples/simple_queries.py
navalmartin_mir_db_utils/examples/use_transaction.py
navalmartin_mir_db_utils/schemata/__init__.py
navalmartin_mir_db_utils/schemata/task_configuration_schema.py
navalmartin_mir_db_utils/schemata/task_performance_result_schema.py
navalmartin_mir_db_utils/schemata/task_result_schema.py
navalmartin_mir_db_utils/schemata/data_views/__init__.py
navalmartin_mir_db_utils/schemata/data_views/indexed_item_data_view_base.py
navalmartin_mir_db_utils/transanctions/__init__.py
navalmartin_mir_db_utils/transanctions/decorators.py
navalmartin_mir_db_utils/transanctions/mongodb_transactions.py
navalmartin_mir_db_utils/utils/__init__.py
navalmartin_mir_db_utils/utils/db_enums.py
navalmartin_mir_db_utils/utils/exceptions.py
navalmartin_mir_db_utils/utils/transform_utils.py
navalmartin_mir_db_utils-0.0.42.dist-info/METADATA
navalmartin_mir_db_utils-0.0.42.dist-info/WHEEL
navalmartin_mir_db_utils-0.0.42.dist-info/licenses/LICENSE
navalmartin_mir_db_utils-0.0.42.dist-info/RECORD
