Metadata-Version: 2.1
Name: navalmartin_mir_db_utils
Version: 0.0.42
Summary: Persistence layer utilities for mir project
Project-URL: Homepage, https://github.com/Navalmartin/mir_persistence_layer_utils
Project-URL: Bug Tracker, https://github.com/Navalmartin/mir_persistence_layer_utils/issues
Author-email: Alexandros Giavaras <a.giavaras@gmail.com>
Maintainer-email: Alexandros Giavaras <a.giavaras@gmail.com>
License-File: LICENSE
Classifier: License :: OSI Approved :: MIT License
Classifier: Operating System :: OS Independent
Classifier: Programming Language :: Python :: 3
Requires-Python: >=3.6
